migration_lint/__init__.py
migration_lint/analyzer/__init__.py
migration_lint/analyzer/base.py
migration_lint/analyzer/compat.py
migration_lint/analyzer/squawk.py
migration_lint/bin/squawk-darwin-arm64
migration_lint/bin/squawk-linux-x86
migration_lint/django/__init__.py
migration_lint/django/apps.py
migration_lint/django/extractor/__init__.py
migration_lint/django/extractor/django_management.py
migration_lint/django/management/__init__.py
migration_lint/django/management/commands/__init__.py
migration_lint/django/management/commands/migration_lint.py
migration_lint/extractor/__init__.py
migration_lint/extractor/alembic.py
migration_lint/extractor/base.py
migration_lint/extractor/django.py
migration_lint/extractor/flyway.py
migration_lint/extractor/model.py
migration_lint/extractor/raw_sql.py
migration_lint/main.py
migration_lint/source_loader/__init__.py
migration_lint/source_loader/base.py
migration_lint/source_loader/gitlab.py
migration_lint/source_loader/local.py
migration_lint/source_loader/model.py
migration_lint/sql/__init__.py
migration_lint/sql/constants.py
migration_lint/sql/model.py
migration_lint/sql/operations.py
migration_lint/sql/parser.py
migration_lint/sql/rules.py
migration_lint/util/__init__.py
migration_lint/util/colors.py
migration_lint/util/env.py
migration_lint-0.2.13.dist-info/LICENSE
migration_lint-0.2.13.dist-info/METADATA
migration_lint-0.2.13.dist-info/WHEEL
migration_lint-0.2.13.dist-info/entry_points.txt
migration_lint-0.2.13.dist-info/RECORD
