Metadata-Version: 2.1
Name: migration-lint
Version: 0.2.13
Summary: Tool for lint operations in DB migrations SQL
Author: Alexey Nikitenko
Author-email: alexey.nikitenko@pandadoc.com
Requires-Python: >=3.9,<4.0
Classifier: Programming Language :: Python :: 3
Classifier: Programming Language :: Python :: 3.9
Classifier: Programming Language :: Python :: 3.10
Classifier: Programming Language :: Python :: 3.11
Classifier: Programming Language :: Python :: 3.12
Provides-Extra: django
Provides-Extra: git
Requires-Dist: click (>=8.0.3,<9.0.0)
Requires-Dist: django (>=3.2) ; extra == "django"
Requires-Dist: gitpython (>=3.1.43,<4.0.0) ; extra == "git"
Requires-Dist: sqlfluff (>=3.2.4,<4.0.0)
